mastercard_assurance_iq-1.0.5.dist-info/DESCRIPTION.rst
mastercard_assurance_iq-1.0.5.dist-info/METADATA
mastercard_assurance_iq-1.0.5.dist-info/RECORD
mastercard_assurance_iq-1.0.5.dist-info/WHEEL
mastercard_assurance_iq-1.0.5.dist-info/metadata.json
mastercard_assurance_iq-1.0.5.dist-info/top_level.txt
mastercardassuranceiq/__init__.py
mastercardassuranceiq/ecommercemessage.py
mastercardassuranceiq/ecommercemessageconfidence.py
mastercardassuranceiq/ecommercemessagescore.py
mastercardassuranceiq/resourceconfig.py
